oeis_sequences/OEISsequences.py
oeis_sequences/__init__.py
oeissequences-0.2.5.6.dist-info/licenses/LICENSE
oeissequences-0.2.5.6.dist-info/METADATA
oeissequences-0.2.5.6.dist-info/WHEEL
oeissequences-0.2.5.6.dist-info/top_level.txt
oeissequences-0.2.5.6.dist-info/RECORD
