Metadata-Version: 2.4
Name: oeissequences
Version: 0.2.5.6
Summary: Python functions to generate OEIS sequences
Home-page: https://github.com/postvakje/oeis-sequences
Author: Chai Wah Wu
Author-email: cwwuieee@gmail.com
License: LICENSE
Classifier: Programming Language :: Python :: 3
Classifier: License :: OSI Approved :: Apache Software License
Classifier: Operating System :: OS Independent
Classifier: Topic :: Scientific/Engineering :: Mathematics
Classifier: Development Status :: 4 - Beta
Requires-Python: >= 3.8
License-File: LICENSE
Requires-Dist: sympy
Requires-Dist: gmpy2
Requires-Dist: num2words
Requires-Dist: unidecode
Requires-Dist: networkx
Requires-Dist: bitarray
Requires-Dist: python-sat
Dynamic: author
Dynamic: author-email
Dynamic: classifier
Dynamic: description
Dynamic: description-content-type
Dynamic: home-page
Dynamic: license
Dynamic: license-file
Dynamic: requires-dist
Dynamic: requires-python
Dynamic: summary
